omop2obo/__init__.py
omop2obo/__version__.py
omop2obo/clinical_concept_annotator.py
omop2obo/ontology_downloader.py
omop2obo/ontology_explorer.py
omop2obo/string_similarity.py
omop2obo/utils/__init__.py
omop2obo/utils/data_utils.py
omop2obo/utils/ontology_utils.py
omop2obo/utils/umls_api.py
omop2obo-1.0.0.dist-info/LICENSE
omop2obo-1.0.0.dist-info/METADATA
omop2obo-1.0.0.dist-info/WHEEL
omop2obo-1.0.0.dist-info/top_level.txt
omop2obo-1.0.0.dist-info/RECORD
