Metadata-Version: 2.1
Name: omop2obo
Version: 1.0.0
Summary: OMOP2OBO is the first health system-wide, disease-agnostic mappings between standardized clinical terminologies in the Observational Medical Outcomes Partnership (OMOP) common data model and several Open Biomedical Ontologies (OBO).
Home-page: https://github.com/callahantiff/OMOP2OBO
Author: Tiffany J. Callahan
Author-email: tiffany.callahan@cuanschutz.edu
License: MIT
Keywords: omop,omop-cdm,formal-logic,biomedical-applications,open-biomedical-ontologies,obofoundry,clinical-terminologies,
Platform: UNKNOWN
Classifier: Development Status :: 3 - Alpha
Classifier: License :: OSI Approved :: MIT License
Classifier: Programming Language :: Python :: 3
License-File: LICENSE
Requires-Dist: click (==8.0.0a1)
Requires-Dist: lxml (==4.6.2)
Requires-Dist: more-itertools (==8.6.0)
Requires-Dist: nltk (==3.6.5)
Requires-Dist: oauth2client (==4.1.3)
Requires-Dist: openpyxl (==3.0.5)
Requires-Dist: pandas (==1.1.5)
Requires-Dist: rdflib (==5.0.0)
Requires-Dist: regex (>=2021.8.3)
Requires-Dist: responses (==0.10.12)
Requires-Dist: scipy (==1.5.4)
Requires-Dist: scikit-learn (==0.23.2)
Requires-Dist: tqdm (==4.54.1)
Requires-Dist: types-requests
Provides-Extra: test
Requires-Dist: codacy-coverage ; extra == 'test'
Requires-Dist: coveralls ; extra == 'test'
Requires-Dist: mock ; extra == 'test'
Requires-Dist: mypy ; extra == 'test'
Requires-Dist: pytest ; extra == 'test'
Requires-Dist: pytest-cov ; extra == 'test'
Requires-Dist: validate-version-code ; extra == 'test'
